wavin_sentio_proxy/__init__.py
wavin_sentio_proxy/const.py
wavin_sentio_proxy/wavin_sentio_proxy.py
wavin_sentio_proxy-0.1.0.dist-info/LICENSE
wavin_sentio_proxy-0.1.0.dist-info/METADATA
wavin_sentio_proxy-0.1.0.dist-info/WHEEL
wavin_sentio_proxy-0.1.0.dist-info/top_level.txt
wavin_sentio_proxy-0.1.0.dist-info/RECORD
