Metadata-Version: 2.1
Name: wavin_sentio_proxy
Version: 0.1.0
Summary: A library to interface with Wavin Sentio floor heating systems.
Home-page: https://github.com/HairingX/wavin_sentio_proxy
Author: HairingX
License: GPLv3
Keywords: Wavin,Sentio,floor-heating,controller,library,Home Automation
Classifier: Development Status :: 3 - Alpha
Classifier: Programming Language :: Python :: 3.12
Classifier: Intended Audience :: Developers
Classifier: Topic :: Software Development :: Libraries
Classifier: License :: OSI Approved :: GNU General Public License v3 (GPLv3)
Requires-Python: >=3.12
License-File: LICENSE
